{"assets/icons/.DS_Store":["assets/icons/.DS_Store"],"assets/icons/chevron_left.svg":["assets/icons/chevron_left.svg"],"assets/icons/close.svg":["assets/icons/close.svg"],"assets/icons/error.svg":["assets/icons/error.svg"],"assets/icons/image_icon.svg":["assets/icons/image_icon.svg"],"assets/icons/info_dark.svg":["assets/icons/info_dark.svg"],"assets/icons/info_light.svg":["assets/icons/info_light.svg"],"assets/icons/pencil.svg":["assets/icons/pencil.svg"],"assets/icons/save.svg":["assets/icons/save.svg"],"assets/icons/search.svg":["assets/icons/search.svg"],"assets/icons/success.svg":["assets/icons/success.svg"],"assets/icons/visibility.svg":["assets/icons/visibility.svg"],"assets/images/.DS_Store":["assets/images/.DS_Store"],"assets/images/empty_notes-optimized.svg":["assets/images/empty_notes-optimized.svg"],"assets/images/empty_search-optimized.svg":["assets/images/empty_search-optimized.svg"],"assets/images/logo.svg":["assets/images/logo.svg"],"packages/cupertino_icons/assets/CupertinoIcons.ttf":["packages/cupertino_icons/assets/CupertinoIcons.ttf"]}